{"start":"S154","seq":["B4-2.0","D5-2.0","A4-2.0","D5-2.0","B4-1.0","G4-1.0","F#4-1.0","r-1.0","r-2.0","D4-2.0","G4-0.5","A4-0.5","B4-1.0","G4-0.5","A4-0.5","B4-1.0","A4-0.5","A4-0.5","G4-2.0","r-1.0"],"runtime":560.6562459468842,"rules":[{"lhs":"S43","ruletype":"AAB","params":[{"symbtype":"T","value":"A4-0.5"},{"symbtype":"T","value":"G4-2.0"}]},{"lhs":"S52","ruletype":"AB","params":[{"symbtype":"T","value":"D4-2.0"},{"symbtype":"NT","value":"S158"}]},{"lhs":"S54","ruletype":"AB","params":[{"symbtype":"T","value":"G4-1.0"},{"symbtype":"NT","value":"S171"}]},{"lhs":"S78","ruletype":"AB","params":[{"symbtype":"T","value":"B4-2.0"},{"symbtype":"NT","value":"S160"}]},{"lhs":"S81","ruletype":"AB","params":[{"symbtype":"T","value":"B4-1.0"},{"symbtype":"NT","value":"S54"}]},{"lhs":"S97","ruletype":"AB","params":[{"symbtype":"T","value":"G4-0.5"},{"symbtype":"NT","value":"S169"}]},{"lhs":"S122","ruletype":"ABA","params":[{"symbtype":"T","value":"r-1.0"},{"symbtype":"NT","value":"S180"}]},{"lhs":"S154","ruletype":"AB","params":[{"symbtype":"NT","value":"S78"},{"symbtype":"NT","value":"S81"}]},{"lhs":"S158","ruletype":"AAB","params":[{"symbtype":"NT","value":"S97"},{"symbtype":"NT","value":"S43"}]},{"lhs":"S160","ruletype":"ABA","params":[{"symbtype":"T","value":"D5-2.0"},{"symbtype":"T","value":"A4-2.0"}]},{"lhs":"S169","ruletype":"AB","params":[{"symbtype":"T","value":"A4-0.5"},{"symbtype":"T","value":"B4-1.0"}]},{"lhs":"S171","ruletype":"AB","params":[{"symbtype":"T","value":"F#4-1.0"},{"symbtype":"NT","value":"S122"}]},{"lhs":"S180","ruletype":"AB","params":[{"symbtype":"T","value":"r-2.0"},{"symbtype":"NT","value":"S52"}]}]}