{"start":"S42","seq":["D4-1.0","G4-1.0","A4-1.0","B4-0.75","F#4-0.25","A4-1.0","G4-1.0","F#4-1.0","E4-1.0","D4-1.0","E4-1.0","F#4-1.0","G4-0.75","A4-0.25","B4-1.0","F#4-1.0","A4-1.0","G4-1.0"],"runtime":78.52412486076355,"rules":[{"lhs":"S2","ruletype":"AB","params":[{"symbtype":"NT","value":"S16"},{"symbtype":"T","value":"G4-0.75"}]},{"lhs":"S3","ruletype":"ABA","params":[{"symbtype":"T","value":"A4-1.0"},{"symbtype":"NT","value":"S6"}]},{"lhs":"S6","ruletype":"AB","params":[{"symbtype":"NT","value":"S43"},{"symbtype":"T","value":"F#4-1.0"}]},{"lhs":"S16","ruletype":"ABA","params":[{"symbtype":"T","value":"F#4-1.0"},{"symbtype":"NT","value":"S79"}]},{"lhs":"S19","ruletype":"AB","params":[{"symbtype":"T","value":"F#4-0.25"},{"symbtype":"NT","value":"S30"}]},{"lhs":"S24","ruletype":"AB","params":[{"symbtype":"NT","value":"S19"},{"symbtype":"T","value":"B4-1.0"}]},{"lhs":"S30","ruletype":"AB","params":[{"symbtype":"T","value":"A4-1.0"},{"symbtype":"NT","value":"S32"}]},{"lhs":"S32","ruletype":"AB","params":[{"symbtype":"NT","value":"S93"},{"symbtype":"T","value":"A4-0.25"}]},{"lhs":"S42","ruletype":"AB","params":[{"symbtype":"T","value":"D4-1.0"},{"symbtype":"NT","value":"S85"}]},{"lhs":"S43","ruletype":"AB","params":[{"symbtype":"T","value":"B4-0.75"},{"symbtype":"NT","value":"S24"}]},{"lhs":"S79","ruletype":"ABA","params":[{"symbtype":"T","value":"E4-1.0"},{"symbtype":"T","value":"D4-1.0"}]},{"lhs":"S85","ruletype":"ABA","params":[{"symbtype":"T","value":"G4-1.0"},{"symbtype":"NT","value":"S3"}]},{"lhs":"S93","ruletype":"AB","params":[{"symbtype":"T","value":"G4-1.0"},{"symbtype":"NT","value":"S2"}]}]}