{"start":"S9","seq":["G4-1.0","F#4-1.0","E4-1.0","D4-1.0","C#4-1.0","D4-1.0","E4-1.0","G4-2.0","E4-3.0","F#4-1.0","C#4-1.0","D4-1.0","E4-2.0","D4-3.0"],"runtime":1.4870858192443848,"rules":[{"lhs":"S3","ruletype":"ABA","params":[{"symbtype":"T","value":"E4-1.0"},{"symbtype":"NT","value":"S49"}]},{"lhs":"S9","ruletype":"AB","params":[{"symbtype":"NT","value":"S18"},{"symbtype":"T","value":"D4-3.0"}]},{"lhs":"S18","ruletype":"AB","params":[{"symbtype":"T","value":"G4-1.0"},{"symbtype":"NT","value":"S22"}]},{"lhs":"S20","ruletype":"AB","params":[{"symbtype":"NT","value":"S3"},{"symbtype":"T","value":"G4-2.0"}]},{"lhs":"S22","ruletype":"AB","params":[{"symbtype":"NT","value":"S71"},{"symbtype":"T","value":"E4-2.0"}]},{"lhs":"S38","ruletype":"AB","params":[{"symbtype":"NT","value":"S61"},{"symbtype":"T","value":"C#4-1.0"}]},{"lhs":"S40","ruletype":"AB","params":[{"symbtype":"NT","value":"S20"},{"symbtype":"T","value":"E4-3.0"}]},{"lhs":"S49","ruletype":"ABA","params":[{"symbtype":"T","value":"D4-1.0"},{"symbtype":"T","value":"C#4-1.0"}]},{"lhs":"S61","ruletype":"ABA","params":[{"symbtype":"T","value":"F#4-1.0"},{"symbtype":"NT","value":"S40"}]},{"lhs":"S71","ruletype":"AB","params":[{"symbtype":"NT","value":"S38"},{"symbtype":"T","value":"D4-1.0"}]}]}