{"start":"S136","seq":["G3-0.5","C4-0.5","B3-0.5","A3-0.5","G3-0.75","E3-0.25","C3-0.5","D3-0.75","E3-0.25","F3-0.5","F3-0.5","E3-0.5","G3-0.5","A3-0.5","B3-0.5","C4-0.5","G3-0.5","G3-0.5","C4-0.5","D4-0.5","D4-0.5","E4-0.5","C4-1.0"],"runtime":6064.011615037918,"rules":[{"lhs":"S51","ruletype":"ABA","params":[{"symbtype":"T","value":"E3-0.25"},{"symbtype":"NT","value":"S88"}]},{"lhs":"S53","ruletype":"AB","params":[{"symbtype":"T","value":"E3-0.5"},{"symbtype":"T","value":"G3-0.5"}]},{"lhs":"S65","ruletype":"AAB","params":[{"symbtype":"T","value":"F3-0.5"},{"symbtype":"NT","value":"S53"}]},{"lhs":"S84","ruletype":"ABA","params":[{"symbtype":"T","value":"A3-0.5"},{"symbtype":"NT","value":"S94"}]},{"lhs":"S88","ruletype":"AB","params":[{"symbtype":"T","value":"C3-0.5"},{"symbtype":"T","value":"D3-0.75"}]},{"lhs":"S94","ruletype":"AB","params":[{"symbtype":"NT","value":"S193"},{"symbtype":"NT","value":"S65"}]},{"lhs":"S123","ruletype":"AB","params":[{"symbtype":"NT","value":"S168"},{"symbtype":"T","value":"E4-0.5"}]},{"lhs":"S134","ruletype":"AB","params":[{"symbtype":"NT","value":"S123"},{"symbtype":"T","value":"C4-1.0"}]},{"lhs":"S136","ruletype":"AB","params":[{"symbtype":"NT","value":"S251"},{"symbtype":"NT","value":"S223"}]},{"lhs":"S168","ruletype":"ABB","params":[{"symbtype":"NT","value":"S188"},{"symbtype":"T","value":"D4-0.5"}]},{"lhs":"S188","ruletype":"ABBA","params":[{"symbtype":"T","value":"C4-0.5"},{"symbtype":"T","value":"G3-0.5"}]},{"lhs":"S193","ruletype":"AB","params":[{"symbtype":"T","value":"G3-0.75"},{"symbtype":"NT","value":"S51"}]},{"lhs":"S222","ruletype":"ABA","params":[{"symbtype":"T","value":"B3-0.5"},{"symbtype":"NT","value":"S84"}]},{"lhs":"S223","ruletype":"AB","params":[{"symbtype":"NT","value":"S222"},{"symbtype":"NT","value":"S134"}]},{"lhs":"S251","ruletype":"AB","params":[{"symbtype":"T","value":"G3-0.5"},{"symbtype":"T","value":"C4-0.5"}]}]}