{"start":"S129","seq":["E4-0.5","C#5-1.0","B4-0.5","A4-0.5","F#4-1.5","F#4-0.5","D5-1.0","B4-0.5","B#4-0.5","C#5-1.5","C#5-0.5","C#5-1.0","A#4-0.5","F#4-0.5","F#5-1.0","B4-0.5","B4-0.5","D5-1.0","B4-0.5","C#5-0.5","A4-1.5"],"runtime":7097.272192955017,"rules":[{"lhs":"S74","ruletype":"AB","params":[{"symbtype":"NT","value":"S148"},{"symbtype":"T","value":"A#4-0.5"}]},{"lhs":"S85","ruletype":"ABA","params":[{"symbtype":"T","value":"B4-0.5"},{"symbtype":"NT","value":"S101"}]},{"lhs":"S100","ruletype":"AB","params":[{"symbtype":"NT","value":"S85"},{"symbtype":"T","value":"B#4-0.5"}]},{"lhs":"S101","ruletype":"AB","params":[{"symbtype":"NT","value":"S109"},{"symbtype":"T","value":"D5-1.0"}]},{"lhs":"S109","ruletype":"AB","params":[{"symbtype":"NT","value":"S176"},{"symbtype":"T","value":"F#4-0.5"}]},{"lhs":"S122","ruletype":"AB","params":[{"symbtype":"NT","value":"S125"},{"symbtype":"NT","value":"S158"}]},{"lhs":"S125","ruletype":"AB","params":[{"symbtype":"NT","value":"S193"},{"symbtype":"T","value":"F#5-1.0"}]},{"lhs":"S129","ruletype":"AB","params":[{"symbtype":"NT","value":"S197"},{"symbtype":"T","value":"A4-1.5"}]},{"lhs":"S148","ruletype":"AB","params":[{"symbtype":"T","value":"E4-0.5"},{"symbtype":"NT","value":"S178"}]},{"lhs":"S158","ruletype":"AABA","params":[{"symbtype":"T","value":"B4-0.5"},{"symbtype":"T","value":"D5-1.0"}]},{"lhs":"S159","ruletype":"AB","params":[{"symbtype":"NT","value":"S100"},{"symbtype":"T","value":"C#5-1.5"}]},{"lhs":"S176","ruletype":"AB","params":[{"symbtype":"T","value":"A4-0.5"},{"symbtype":"T","value":"F#4-1.5"}]},{"lhs":"S178","ruletype":"ABA","params":[{"symbtype":"T","value":"C#5-1.0"},{"symbtype":"NT","value":"S198"}]},{"lhs":"S193","ruletype":"AB","params":[{"symbtype":"NT","value":"S74"},{"symbtype":"T","value":"F#4-0.5"}]},{"lhs":"S197","ruletype":"AB","params":[{"symbtype":"NT","value":"S122"},{"symbtype":"T","value":"C#5-0.5"}]},{"lhs":"S198","ruletype":"AB","params":[{"symbtype":"NT","value":"S159"},{"symbtype":"T","value":"C#5-0.5"}]}]}