{"start":"S134","seq":["D5-8.0","A4-8.0","C5-4.0","Bb4-4.0","D5-8.0","A4-8.0","C5-4.0","Bb4-4.0","A4-2.0","C5-2.0","Bb4-2.0","A4-2.0","G4-8.0","C5-8.0","C5-8.0","Bb4-8.0","Bb4-8.0","A4-2.0","A4-2.0","F4-2.0","G4-4.0","G4-2.0","F4-8.0"],"runtime":5288.791527032852,"rules":[{"lhs":"S9","ruletype":"AB","params":[{"symbtype":"T","value":"G4-2.0"},{"symbtype":"T","value":"F4-8.0"}]},{"lhs":"S13","ruletype":"AAB","params":[{"symbtype":"T","value":"A4-2.0"},{"symbtype":"NT","value":"S68"}]},{"lhs":"S26","ruletype":"AB","params":[{"symbtype":"NT","value":"S37"},{"symbtype":"NT","value":"S104"}]},{"lhs":"S37","ruletype":"AB","params":[{"symbtype":"NT","value":"S239"},{"symbtype":"T","value":"G4-8.0"}]},{"lhs":"S47","ruletype":"AB","params":[{"symbtype":"T","value":"D5-8.0"},{"symbtype":"NT","value":"S157"}]},{"lhs":"S68","ruletype":"AB","params":[{"symbtype":"NT","value":"S242"},{"symbtype":"NT","value":"S9"}]},{"lhs":"S93","ruletype":"AB","params":[{"symbtype":"T","value":"C5-4.0"},{"symbtype":"T","value":"Bb4-4.0"}]},{"lhs":"S104","ruletype":"AAB","params":[{"symbtype":"T","value":"C5-8.0"},{"symbtype":"NT","value":"S217"}]},{"lhs":"S134","ruletype":"AAB","params":[{"symbtype":"NT","value":"S47"},{"symbtype":"NT","value":"S26"}]},{"lhs":"S147","ruletype":"AB","params":[{"symbtype":"T","value":"C5-2.0"},{"symbtype":"T","value":"Bb4-2.0"}]},{"lhs":"S157","ruletype":"AB","params":[{"symbtype":"T","value":"A4-8.0"},{"symbtype":"NT","value":"S93"}]},{"lhs":"S217","ruletype":"AAB","params":[{"symbtype":"T","value":"Bb4-8.0"},{"symbtype":"NT","value":"S13"}]},{"lhs":"S239","ruletype":"ABA","params":[{"symbtype":"T","value":"A4-2.0"},{"symbtype":"NT","value":"S147"}]},{"lhs":"S242","ruletype":"AB","params":[{"symbtype":"T","value":"F4-2.0"},{"symbtype":"T","value":"G4-4.0"}]}]}