{"start":"S91","seq":["G4-0.5","A4-0.5","B4-1.0","D5-1.0","C5-0.5","B4-0.5","B4-1.0","A4-1.0","B4-0.5","A4-0.5","G4-1.0","A4-0.5","C5-0.5","B4-0.5","A4-0.5","G4-2.0"],"runtime":9.927068948745728,"rules":[{"lhs":"S25","ruletype":"ABA","params":[{"symbtype":"T","value":"A4-0.5"},{"symbtype":"NT","value":"S74"}]},{"lhs":"S34","ruletype":"AB","params":[{"symbtype":"T","value":"C5-0.5"},{"symbtype":"T","value":"B4-0.5"}]},{"lhs":"S47","ruletype":"AB","params":[{"symbtype":"NT","value":"S110"},{"symbtype":"T","value":"A4-1.0"}]},{"lhs":"S57","ruletype":"AB","params":[{"symbtype":"T","value":"G4-0.5"},{"symbtype":"NT","value":"S109"}]},{"lhs":"S73","ruletype":"AB","params":[{"symbtype":"NT","value":"S25"},{"symbtype":"T","value":"G4-1.0"}]},{"lhs":"S74","ruletype":"AB","params":[{"symbtype":"NT","value":"S47"},{"symbtype":"T","value":"B4-0.5"}]},{"lhs":"S81","ruletype":"AB","params":[{"symbtype":"T","value":"D5-1.0"},{"symbtype":"NT","value":"S34"}]},{"lhs":"S90","ruletype":"ABA","params":[{"symbtype":"T","value":"A4-0.5"},{"symbtype":"NT","value":"S34"}]},{"lhs":"S91","ruletype":"AB","params":[{"symbtype":"NT","value":"S57"},{"symbtype":"T","value":"G4-2.0"}]},{"lhs":"S109","ruletype":"AB","params":[{"symbtype":"NT","value":"S73"},{"symbtype":"NT","value":"S90"}]},{"lhs":"S110","ruletype":"ABA","params":[{"symbtype":"T","value":"B4-1.0"},{"symbtype":"NT","value":"S81"}]}]}